LICENSE
README.md
setup.py
marketstack/__init__.py
marketstack/client.py
marketstack/types.py
marketstack.egg-info/PKG-INFO
marketstack.egg-info/SOURCES.txt
marketstack.egg-info/dependency_links.txt
marketstack.egg-info/requires.txt
marketstack.egg-info/top_level.txt
marketstack/api/__init__.py
marketstack/api/currencies/__init__.py
marketstack/api/currencies/currencies.py
marketstack/api/dividends/__init__.py
marketstack/api/dividends/dividends.py
marketstack/api/eod/__init__.py
marketstack/api/eod/eod.py
marketstack/api/eod/eod_date.py
marketstack/api/eod/eod_latest.py
marketstack/api/exchanges/__init__.py
marketstack/api/exchanges/exchange_mic.py
marketstack/api/exchanges/exchange_mic_eod.py
marketstack/api/exchanges/exchange_mic_eod_date.py
marketstack/api/exchanges/exchange_mic_eod_latest.py
marketstack/api/exchanges/exchange_mic_intraday.py
marketstack/api/exchanges/exchange_mic_intraday_date.py
marketstack/api/exchanges/exchange_mic_intraday_latest.py
marketstack/api/exchanges/exchange_mic_tickers.py
marketstack/api/exchanges/exchanges.py
marketstack/api/intraday/__init__.py
marketstack/api/intraday/intraday.py
marketstack/api/intraday/intraday_date.py
marketstack/api/intraday/intraday_latest.py
marketstack/api/splits/__init__.py
marketstack/api/splits/splits.py
marketstack/api/tickers/__init__.py
marketstack/api/tickers/ticker_symbol.py
marketstack/api/tickers/ticker_symbol_dividends.py
marketstack/api/tickers/ticker_symbol_eod.py
marketstack/api/tickers/ticker_symbol_eod_date.py
marketstack/api/tickers/ticker_symbol_eod_latest.py
marketstack/api/tickers/ticker_symbol_intraday.py
marketstack/api/tickers/ticker_symbol_intraday_date.py
marketstack/api/tickers/ticker_symbol_intraday_latest.py
marketstack/api/tickers/ticker_symbol_splits.py
marketstack/api/tickers/tickers.py
marketstack/api/timezones/__init__.py
marketstack/api/timezones/timezones.py
marketstack/models/__init__.py
marketstack/models/currency.py
marketstack/models/dividend.py
marketstack/models/eod_price.py
marketstack/models/error.py
marketstack/models/error_code.py
marketstack/models/error_context.py
marketstack/models/error_response.py
