Metadata-Version: 2.1
Name: marketstack
Version: 0.6
Summary: Inofficial Marketstack OpenAPI Python client
Home-page: https://github.com/mreiche/marketstack-python
Author: Mike Reiche
License-File: LICENSE
